neon_homeassistant_skill/__init__.py
neon_homeassistant_skill/locale/en-us/dialog/acknowledge.dialog
neon_homeassistant_skill/locale/en-us/dialog/area.dashboard.opened.dialog
neon_homeassistant_skill/locale/en-us/dialog/area.not.found.dialog
neon_homeassistant_skill/locale/en-us/dialog/assist.dialog
neon_homeassistant_skill/locale/en-us/dialog/assist.error.dialog
neon_homeassistant_skill/locale/en-us/dialog/assist.not.understood.dialog
neon_homeassistant_skill/locale/en-us/dialog/device.not.found.dialog
neon_homeassistant_skill/locale/en-us/dialog/device.status.dialog
neon_homeassistant_skill/locale/en-us/dialog/device.turned.off.dialog
neon_homeassistant_skill/locale/en-us/dialog/device.turned.on.dialog
neon_homeassistant_skill/locale/en-us/dialog/disable.dialog
neon_homeassistant_skill/locale/en-us/dialog/enable.dialog
neon_homeassistant_skill/locale/en-us/dialog/ha.dashboard.closed.dialog
neon_homeassistant_skill/locale/en-us/dialog/ha.dashboard.opened.dialog
neon_homeassistant_skill/locale/en-us/dialog/lights.current.brightness.dialog
neon_homeassistant_skill/locale/en-us/dialog/lights.current.color.dialog
neon_homeassistant_skill/locale/en-us/dialog/lights.status.not.available.dialog
neon_homeassistant_skill/locale/en-us/dialog/no.parsed.device.dialog
neon_homeassistant_skill/locale/en-us/dialog/vacuum.action.not.found.dialog
neon_homeassistant_skill/locale/en-us/intents/assist.intent
neon_homeassistant_skill/locale/en-us/intents/close.dashboard.intent
neon_homeassistant_skill/locale/en-us/intents/disable.intent
neon_homeassistant_skill/locale/en-us/intents/enable.intent
neon_homeassistant_skill/locale/en-us/intents/get.all.devices.intent
neon_homeassistant_skill/locale/en-us/intents/lights.decrease.brightness.intent
neon_homeassistant_skill/locale/en-us/intents/lights.get.brightness.intent
neon_homeassistant_skill/locale/en-us/intents/lights.get.color.intent
neon_homeassistant_skill/locale/en-us/intents/lights.increase.brightness.intent
neon_homeassistant_skill-0.0.23.dist-info/LICENSE
neon_homeassistant_skill-0.0.23.dist-info/METADATA
neon_homeassistant_skill-0.0.23.dist-info/WHEEL
neon_homeassistant_skill-0.0.23.dist-info/entry_points.txt
neon_homeassistant_skill-0.0.23.dist-info/RECORD
