Metadata-Version: 2.1
Name: neon-homeassistant-skill
Version: 0.0.23
Summary: An OVOS/Neon.AI Skill for Home Assistant, which integrates with ovos-PHAL-plugin-homeassistant.
License: Apache-2.0
Keywords: ovos,neon,home,assistant,phal,voice,interface,skill,plugin
Author: Mike Gray
Author-email: mike@graywind.org
Requires-Python: >=3.9,<4.0
Classifier: License :: OSI Approved :: Apache Software License
Classifier: Programming Language :: Python :: 3
Classifier: Programming Language :: Python :: 3.9
Classifier: Programming Language :: Python :: 3.10
Classifier: Programming Language :: Python :: 3.11
Classifier: Programming Language :: Python :: 3.12
Classifier: Programming Language :: Python :: 3.13
Provides-Extra: test
Requires-Dist: ovos-bus-client
Requires-Dist: ovos-workshop (>=0.0.15)
Requires-Dist: setuptools (>=75.0.0,<76.0.0)
